abcdrl/__init__.py
abcdrl/ddpg.py
abcdrl/ddqn.py
abcdrl/dqn.py
abcdrl/dqn_atari.py
abcdrl/pdqn.py
abcdrl/ppo.py
abcdrl/sac.py
abcdrl/td3.py
abcdrl-0.2.0a4.dist-info/METADATA
abcdrl-0.2.0a4.dist-info/LICENSE
abcdrl-0.2.0a4.dist-info/WHEEL
abcdrl-0.2.0a4.dist-info/RECORD
