Metadata-Version: 2.1
Name: abcdrl
Version: 0.2.0a4
Summary: Modular Single-file Reinfocement Learning Algorithms Library
Home-page: https://abcdrl.xyz/
License: MIT
Keywords: reinforcement,machine,learning
Author: Adam Zhao
Author-email: pazyx728@gmail.com
Maintainer: Adam Zhao
Maintainer-email: pazyx728@gmail.com
Requires-Python: >=3.8,<3.11
Classifier: Development Status :: 4 - Beta
Classifier: Framework :: Pytest
Classifier: Intended Audience :: Developers
Classifier: Intended Audience :: Science/Research
Classifier: License :: OSI Approved :: MIT License
Classifier: Natural Language :: Chinese (Simplified)
Classifier: Natural Language :: English
Classifier: Operating System :: MacOS
Classifier: Operating System :: POSIX :: Linux
Classifier: Programming Language :: Python :: 3
Classifier: Programming Language :: Python :: 3.8
Classifier: Programming Language :: Python :: 3.9
Classifier: Programming Language :: Python :: 3.10
Classifier: Programming Language :: Python :: 3.10
Classifier: Programming Language :: Python :: 3.8
Classifier: Programming Language :: Python :: 3.9
Classifier: Topic :: Scientific/Engineering :: Artificial Intelligence
Classifier: Topic :: Software Development :: Libraries :: Python Modules
Provides-Extra: all
Provides-Extra: atari
Provides-Extra: mujoco
Provides-Extra: torch
Requires-Dist: autorom[accept-rom-license] (>=0.4.2,<0.5.0) ; extra == "atari" or extra == "all"
Requires-Dist: combine_signatures (>=0.1.0,<0.2.0)
Requires-Dist: dill (>=0.3.6,<0.4.0)
Requires-Dist: fire (>=0.5.0,<0.6.0)
Requires-Dist: free-mujoco-py (==2.1.6) ; extra == "mujoco" or extra == "all"
Requires-Dist: gymnasium (>=0.27.0,<0.28.0)
Requires-Dist: imageio (>=2.14.1) ; extra == "mujoco" or extra == "all"
Requires-Dist: moviepy (>=1.0.0)
Requires-Dist: mujoco (>=2.3.1.post1) ; extra == "mujoco" or extra == "all"
Requires-Dist: mujoco-py (>=2.1,<2.2) ; extra == "mujoco" or extra == "all"
Requires-Dist: opencv-python (>=3.0)
Requires-Dist: pygame (==2.1.3.dev8)
Requires-Dist: shimmy[atari] (>=0.1.0,<1.0) ; extra == "atari" or extra == "all"
Requires-Dist: tensorboard (>=2.10.0,<3.0.0)
Requires-Dist: torch (>=1.12.1,<2.0.0) ; extra == "torch" or extra == "all"
Requires-Dist: wandb (>=0.13.7,<0.14.0)
Project-URL: Bug Tracker, https://github.com/sdpkjc/abcdrl/issues
Project-URL: Documentation, https://docs.abcdrl.xyz/
Project-URL: Docker Hub, https://hub.docker.com/r/sdpkjc/abcdrl/
Project-URL: Mirror Git Repo, https://gitee.com/sdpkjc/abcdrl/
Project-URL: Repository, https://github.com/sdpkjc/abcdrl
